indexclient/__init__.py
indexclient/chroma.py
indexclient/client.py
indexclient/config.py
indexclient/demo.py
indexclient/index_types.py
indexclient/utils.py
indexnetwork_sdk-0.0.18.dist-info/METADATA
indexnetwork_sdk-0.0.18.dist-info/WHEEL
indexnetwork_sdk-0.0.18.dist-info/top_level.txt
indexnetwork_sdk-0.0.18.dist-info/RECORD
