Metadata-Version: 2.1
Name: indexnetwork-sdk
Version: 0.0.18
Summary: Index Network SDK
Home-page: https://github.com/indexnetwork/index
Author: Index
Author-email: accounts@index.network
License: UNKNOWN
Platform: UNKNOWN
Requires-Python: >=3.0
Requires-Dist: abnf
Requires-Dist: aiohttp
Requires-Dist: aiosignal
Requires-Dist: annotated-types
Requires-Dist: asn1crypto
Requires-Dist: async-timeout
Requires-Dist: attrs
Requires-Dist: bip-utils
Requires-Dist: bitarray
Requires-Dist: cbor2
Requires-Dist: certifi
Requires-Dist: cffi
Requires-Dist: charset-normalizer
Requires-Dist: ckzg
Requires-Dist: coincurve
Requires-Dist: crcmod
Requires-Dist: crypto
Requires-Dist: cytoolz
Requires-Dist: ecdsa
Requires-Dist: ed25519-blake2b
Requires-Dist: eth-account
Requires-Dist: eth-hash
Requires-Dist: eth-keyfile
Requires-Dist: eth-keys
Requires-Dist: eth-rlp
Requires-Dist: eth-typing
Requires-Dist: eth-utils
Requires-Dist: eth-abi
Requires-Dist: frozenlist
Requires-Dist: hexbytes
Requires-Dist: idna
Requires-Dist: jsonschema
Requires-Dist: jsonschema-specifications
Requires-Dist: lru-dict
Requires-Dist: multidict
Requires-Dist: Naked
Requires-Dist: parsimonious
Requires-Dist: protobuf
Requires-Dist: py-sr25519-bindings
Requires-Dist: py-crypto-hd-wallet
Requires-Dist: pycparser
Requires-Dist: pycryptodome
Requires-Dist: pydantic
Requires-Dist: pydantic-core
Requires-Dist: PyNaCl
Requires-Dist: python-dateutil
Requires-Dist: pyunormalize
Requires-Dist: PyYAML
Requires-Dist: referencing
Requires-Dist: regex
Requires-Dist: requests
Requires-Dist: rlp
Requires-Dist: rpds-py
Requires-Dist: shellescape
Requires-Dist: siwe
Requires-Dist: six
Requires-Dist: toolz
Requires-Dist: typing-extensions
Requires-Dist: urllib3
Requires-Dist: web3
Requires-Dist: websockets
Requires-Dist: wheel
Requires-Dist: yarl
Requires-Dist: langchain-openai
Requires-Dist: langchain-chroma
Requires-Dist: chromadb
Requires-Dist: setuptools
